README.txt
setup.py
qahal/__init__.py
qahal/state_list.py
qahal/utils.py
qahal.egg-info/PKG-INFO
qahal.egg-info/SOURCES.txt
qahal.egg-info/dependency_links.txt
qahal.egg-info/top_level.txt
qahal/state/__init__.py
qahal/state/check_state.py
qahal/state/form_state.py
qahal/state/input_state.py
qahal/state/menu_state.py
qahal/state/router_state.py
qahal/state/state.py