Metadata-Version: 1.1
Name: qahal
Version: 1.0.0
Summary: State machine with variables within states.
Home-page: https://github.com/alghafli/qahal
Author: Mohammad Alghafli
Author-email: thebsom@gmail.com
License: UNKNOWN
Keywords: state machine menu
Platform: UNKNOWN
Classifier: Development Status :: 3 - Alpha
Classifier: Intended Audience :: Developers
Classifier: License :: OSI Approved :: GNU General Public License v3 (GPLv3)
Classifier: Programming Language :: Python :: 3.8
